onamK/__init__.py
onamK/onam.py
onamK-0.0.4.dist-info/METADATA
onamK-0.0.4.dist-info/WHEEL
onamK-0.0.4.dist-info/top_level.txt
onamK-0.0.4.dist-info/RECORD
